topsis_102217115/102217115.py
topsis_102217115/__init__.py
topsis_102217115/topsis_102217115.py
topsis_102217115-1.1.dist-info/Licence.txt
topsis_102217115-1.1.dist-info/METADATA
topsis_102217115-1.1.dist-info/WHEEL
topsis_102217115-1.1.dist-info/top_level.txt
topsis_102217115-1.1.dist-info/RECORD
