Metadata-Version: 2.2
Name: topsis_102217115
Version: 1.1
Summary: This is a package for TOPSIS score calculation
Author: Gurleen
License-File: Licence.txt
Requires-Dist: pandas>=1.0.0
Requires-Dist: numpy>=1.18.0
Dynamic: author
Dynamic: description
Dynamic: description-content-type
Dynamic: requires-dist
Dynamic: summary
